snipd_export_parser.py
snipd_export_parser-0.1.2.dist-info/LICENSE
snipd_export_parser-0.1.2.dist-info/METADATA
snipd_export_parser-0.1.2.dist-info/WHEEL
snipd_export_parser-0.1.2.dist-info/entry_points.txt
snipd_export_parser-0.1.2.dist-info/RECORD
