Metadata-Version: 2.3
Name: snipd_export_parser
Version: 0.1.2
Summary: A tool to parse Snipd export Markdown files into individual chapter files.
License: AGPL-3.0
Author: 菜就多練練
Author-email: im@bgzo.cc
Requires-Python: >=3.9
Classifier: License :: OSI Approved :: GNU Affero General Public License v3
Classifier: Programming Language :: Python :: 3
Classifier: Programming Language :: Python :: 3.9
Classifier: Programming Language :: Python :: 3.10
Classifier: Programming Language :: Python :: 3.11
Classifier: Programming Language :: Python :: 3.12
Classifier: Programming Language :: Python :: 3.13
Requires-Dist: click (>=8.1.8,<9.0.0)
Requires-Dist: pyyaml (>=6.0.2,<6.1.0)
